jugaad_trader/__init__.py
jugaad_trader/cli.py
jugaad_trader/ucli.py
jugaad_trader/upstox.py
jugaad_trader/util.py
jugaad_trader/zcli.py
jugaad_trader/zerodha.py
jugaad_trader-0.19.dist-info/LICENSE.YOLO.md
jugaad_trader-0.19.dist-info/METADATA
jugaad_trader-0.19.dist-info/WHEEL
jugaad_trader-0.19.dist-info/entry_points.txt
jugaad_trader-0.19.dist-info/top_level.txt
jugaad_trader-0.19.dist-info/RECORD
