Metadata-Version: 2.1
Name: jugaad-trader
Version: 0.19
Summary: Free Zerodha API python library
Author-email: jugaad-coder <abc@xyz.com>
License: YOLO LICENSE
Project-URL: Homepage, https://marketsetup.in/documentation/jugaad-trader/
Project-URL: Documentation, https://marketsetup.in/documentation/jugaad-trader/
Project-URL: Repository, https://github.com/jugaad-py/jugaad-trader
Project-URL: Issues, https://github.com/jugaad-py/jugaad-trader/issues
Keywords: Zerodha,kiteconnect,pykiteconnect
Requires-Python: >=3.6
License-File: LICENSE.YOLO.md
Requires-Dist: requests
Requires-Dist: websockets
Requires-Dist: kiteconnect
Requires-Dist: beautifulsoup4
Requires-Dist: Click
Requires-Dist: six
Requires-Dist: pyotp
Requires-Dist: loguru
